{
  "fetchedAt": "2026-04-30T15:44:54.430Z",
  "status": "ok",
  "count": 33,
  "tools": [
    {
      "id": "openapi_amazonaws_com_amplifybackend_amplifybackend.backend.cloneBackend",
      "name": "backend.cloneBackend",
      "description": "This operation clones an existing backend."
    },
    {
      "id": "openapi_amazonaws_com_amplifybackend_amplifybackend.backend.createBackend",
      "name": "backend.createBackend",
      "description": "This operation creates a backend for an Amplify app. Backends are automatically created at the time of app creation."
    },
    {
      "id": "openapi_amazonaws_com_amplifybackend_amplifybackend.backend.createBackendApi",
      "name": "backend.createBackendApi",
      "description": "Creates a new backend API resource."
    },
    {
      "id": "openapi_amazonaws_com_amplifybackend_amplifybackend.backend.createBackendAuth",
      "name": "backend.createBackendAuth",
      "description": "Creates a new backend authentication resource."
    },
    {
      "id": "openapi_amazonaws_com_amplifybackend_amplifybackend.backend.createBackendConfig",
      "name": "backend.createBackendConfig",
      "description": "Creates a config object for a backend."
    },
    {
      "id": "openapi_amazonaws_com_amplifybackend_amplifybackend.backend.createBackendStorage",
      "name": "backend.createBackendStorage",
      "description": "Creates a backend storage resource."
    },
    {
      "id": "openapi_amazonaws_com_amplifybackend_amplifybackend.backend.createToken",
      "name": "backend.createToken",
      "description": "Generates a one-time challenge code to authenticate a user into your Amplify Admin UI."
    },
    {
      "id": "openapi_amazonaws_com_amplifybackend_amplifybackend.backend.deleteBackend",
      "name": "backend.deleteBackend",
      "description": "Removes an existing environment from your Amplify project."
    },
    {
      "id": "openapi_amazonaws_com_amplifybackend_amplifybackend.backend.deleteBackendApi",
      "name": "backend.deleteBackendApi",
      "description": "Deletes an existing backend API resource."
    },
    {
      "id": "openapi_amazonaws_com_amplifybackend_amplifybackend.backend.deleteBackendAuth",
      "name": "backend.deleteBackendAuth",
      "description": "Deletes an existing backend authentication resource."
    },
    {
      "id": "openapi_amazonaws_com_amplifybackend_amplifybackend.backend.deleteBackendStorage",
      "name": "backend.deleteBackendStorage",
      "description": "Removes the specified backend storage resource."
    },
    {
      "id": "openapi_amazonaws_com_amplifybackend_amplifybackend.backend.deleteToken",
      "name": "backend.deleteToken",
      "description": "Deletes the challenge token based on the given appId and sessionId."
    },
    {
      "id": "openapi_amazonaws_com_amplifybackend_amplifybackend.backend.generateBackendApiModels",
      "name": "backend.generateBackendApiModels",
      "description": "Generates a model schema for an existing backend API resource."
    },
    {
      "id": "openapi_amazonaws_com_amplifybackend_amplifybackend.backend.getBackend",
      "name": "backend.getBackend",
      "description": "Provides project-level details for your Amplify UI project."
    },
    {
      "id": "openapi_amazonaws_com_amplifybackend_amplifybackend.backend.getBackendApi",
      "name": "backend.getBackendApi",
      "description": "Gets the details for a backend API."
    },
    {
      "id": "openapi_amazonaws_com_amplifybackend_amplifybackend.backend.getBackendApiModels",
      "name": "backend.getBackendApiModels",
      "description": "Gets a model introspection schema for an existing backend API resource."
    },
    {
      "id": "openapi_amazonaws_com_amplifybackend_amplifybackend.backend.getBackendAuth",
      "name": "backend.getBackendAuth",
      "description": "Gets a backend auth details."
    },
    {
      "id": "openapi_amazonaws_com_amplifybackend_amplifybackend.backend.getBackendJob",
      "name": "backend.getBackendJob",
      "description": "Returns information about a specific job."
    },
    {
      "id": "openapi_amazonaws_com_amplifybackend_amplifybackend.backend.getBackendStorage",
      "name": "backend.getBackendStorage",
      "description": "Gets details for a backend storage resource."
    },
    {
      "id": "openapi_amazonaws_com_amplifybackend_amplifybackend.backend.getToken",
      "name": "backend.getToken",
      "description": "Gets the challenge token based on the given appId and sessionId."
    },
    {
      "id": "openapi_amazonaws_com_amplifybackend_amplifybackend.backend.importBackendAuth",
      "name": "backend.importBackendAuth",
      "description": "Imports an existing backend authentication resource."
    },
    {
      "id": "openapi_amazonaws_com_amplifybackend_amplifybackend.backend.importBackendStorage",
      "name": "backend.importBackendStorage",
      "description": "Imports an existing backend storage resource."
    },
    {
      "id": "openapi_amazonaws_com_amplifybackend_amplifybackend.backend.listBackendJobs",
      "name": "backend.listBackendJobs",
      "description": "Lists the jobs for the backend of an Amplify app."
    },
    {
      "id": "openapi_amazonaws_com_amplifybackend_amplifybackend.backend.removeAllBackends",
      "name": "backend.removeAllBackends",
      "description": "Removes all backend environments from your Amplify project."
    },
    {
      "id": "openapi_amazonaws_com_amplifybackend_amplifybackend.backend.removeBackendConfig",
      "name": "backend.removeBackendConfig",
      "description": "Removes the AWS resources required to access the Amplify Admin UI."
    },
    {
      "id": "openapi_amazonaws_com_amplifybackend_amplifybackend.backend.updateBackendApi",
      "name": "backend.updateBackendApi",
      "description": "Updates an existing backend API resource."
    },
    {
      "id": "openapi_amazonaws_com_amplifybackend_amplifybackend.backend.updateBackendAuth",
      "name": "backend.updateBackendAuth",
      "description": "Updates an existing backend authentication resource."
    },
    {
      "id": "openapi_amazonaws_com_amplifybackend_amplifybackend.backend.updateBackendConfig",
      "name": "backend.updateBackendConfig",
      "description": "Updates the AWS resources required to access the Amplify Admin UI."
    },
    {
      "id": "openapi_amazonaws_com_amplifybackend_amplifybackend.backend.updateBackendJob",
      "name": "backend.updateBackendJob",
      "description": "Updates a specific job."
    },
    {
      "id": "openapi_amazonaws_com_amplifybackend_amplifybackend.backend.updateBackendStorage",
      "name": "backend.updateBackendStorage",
      "description": "Updates an existing backend storage resource."
    },
    {
      "id": "openapi_amazonaws_com_amplifybackend_amplifybackend.s3Buckets.listS3Buckets",
      "name": "s3Buckets.listS3Buckets",
      "description": "The list of S3 buckets in your account."
    },
    {
      "id": "openapi.previewSpec",
      "name": "openapi.previewSpec",
      "description": "Preview an OpenAPI document before adding it as a source"
    },
    {
      "id": "openapi.addSource",
      "name": "openapi.addSource",
      "description": "Add an OpenAPI source and register its operations as tools"
    }
  ]
}