{
  "fetchedAt": "2026-04-30T15:45:16.415Z",
  "status": "ok",
  "count": 3,
  "tools": [
    {
      "id": "openapi_apisetu_gov_in_hpsssb_hpsssb.apIs.adcrd",
      "name": "apIs.adcrd",
      "description": "API to verify Admit Card."
    },
    {
      "id": "openapi.previewSpec",
      "name": "openapi.previewSpec",
      "description": "Preview an OpenAPI document before adding it as a source"
    },
    {
      "id": "openapi.addSource",
      "name": "openapi.addSource",
      "description": "Add an OpenAPI source and register its operations as tools"
    }
  ]
}