{
  "fetchedAt": "2026-04-30T15:22:46.432Z",
  "status": "ok",
  "count": 3,
  "tools": [
    {
      "id": "openapi_interzoid_com_convertcurrency_convertcurrency.liveCurrencyRateConversion.convertcurrency",
      "name": "liveCurrencyRateConversion.convertcurrency",
      "description": "Provide an amount in one currency (EUR, GBP, CNY, JPY, AUD, etc.), and also a second currency to convert it to. The API will return the result using current foreign exchange rates. See the API home page for a list of all supported currencies."
    },
    {
      "id": "openapi.previewSpec",
      "name": "openapi.previewSpec",
      "description": "Preview an OpenAPI document before adding it as a source"
    },
    {
      "id": "openapi.addSource",
      "name": "openapi.addSource",
      "description": "Add an OpenAPI source and register its operations as tools"
    }
  ]
}