{
  "fetchedAt": "2026-04-30T15:22:52.349Z",
  "status": "ok",
  "count": 5,
  "tools": [
    {
      "id": "openapi_nasa_gov_asteroids_neows_asteroids_neows.projects.getApiProjectsIdFormat",
      "name": "projects.getApiProjectsIdFormat",
      "description": "Returns information about a specific technology project."
    },
    {
      "id": "openapi_nasa_gov_asteroids_neows_asteroids_neows.projectsFormat.getApiProjectsFormat",
      "name": "projectsFormat.getApiProjectsFormat",
      "description": "Returns a list of available technology project IDs."
    },
    {
      "id": "openapi_nasa_gov_asteroids_neows_asteroids_neows.root.getApi",
      "name": "root.getApi",
      "description": "Returns the swagger specification for the API."
    },
    {
      "id": "openapi.previewSpec",
      "name": "openapi.previewSpec",
      "description": "Preview an OpenAPI document before adding it as a source"
    },
    {
      "id": "openapi.addSource",
      "name": "openapi.addSource",
      "description": "Add an OpenAPI source and register its operations as tools"
    }
  ]
}